sea_common/__init__.py
sea_common/celery.py
sea_common/config.py
sea_common/sqlalchemy.py
sea_common/strawberry.py
sea_common/utilities.py
sea_common/app/__init__.py
sea_common/db/__init__.py
sea_common/db/base_class.py
sea_common/db/session.py
sea_common-2.0.29.dist-info/LICENSE
sea_common-2.0.29.dist-info/METADATA
sea_common-2.0.29.dist-info/WHEEL
sea_common-2.0.29.dist-info/top_level.txt
sea_common-2.0.29.dist-info/RECORD
