Metadata-Version: 2.1
Name: sea-common
Version: 2.0.29
Summary: SEA Web Services common python packages
Home-page: https://github.com/sea-biopharma/sea-common
Author: SEA Biopharma
Author-email: sea.biopharma@gmail.com
License: UNKNOWN
Project-URL: Bug Tracker, https://github.com/sea-biopharma/sea-common/issues
Platform: UNKNOWN
Requires-Python: >=3.8
License-File: LICENSE
